pilsner/__init__.py
pilsner/model.c
pilsner/model.cp36-win_amd64.pyd
pilsner/model.py
pilsner/utility.c
pilsner/utility.cp36-win_amd64.pyd
pilsner/utility.py
pilsner-0.1.0.dist-info/LICENSE
pilsner-0.1.0.dist-info/METADATA
pilsner-0.1.0.dist-info/WHEEL
pilsner-0.1.0.dist-info/top_level.txt
pilsner-0.1.0.dist-info/RECORD
