Metadata-Version: 2.1
Name: pilsner
Version: 0.1.0
Summary: Utility for dictionary-based named entity recognition
Home-page: https://github.com/pgolo/pilsner
Author: Pavel Golovatenko-Abramov
Author-email: p.golovatenko@gmail.com
License: MIT
Platform: any
Classifier: Development Status :: 4 - Beta
Classifier: Intended Audience :: Developers
Classifier: Topic :: Software Development :: Libraries :: Python Modules
Classifier: Topic :: Text Processing :: Linguistic
Classifier: Programming Language :: Python :: 3.6
Classifier: Programming Language :: Python :: 3.7
Classifier: Programming Language :: Python :: 3.8
Classifier: Programming Language :: Python :: 3.9
Classifier: License :: OSI Approved :: MIT License
Classifier: Operating System :: OS Independent
Requires-Python: >=3.6
Requires-Dist: sic (>=1.2.0)
